policelibrary/__init__.py
policelibrary/asr.py
policelibrary/chat.py
policelibrary/logger.py
tests/draw_bboxes.py
tests/test_asr.py
tests/test_chat.py
policelibrary-0.1.0.dist-info/METADATA
policelibrary-0.1.0.dist-info/WHEEL
policelibrary-0.1.0.dist-info/top_level.txt
policelibrary-0.1.0.dist-info/RECORD
